[
  {
    "offset": 0.0,
    "pitches": [
      "C3",
      "E3",
      "G3"
    ],
    "q_length": 4.0,
    "style": "コードストローク",
    "section": "Verse 1",
    "chord_label": "",
    "velocity_base": 65,
    "humanize_style": "soft",
    "instrument_hint": "guitar",
    "is_fill": false,
    "emotional_description": "静けさ・記憶の霧",
    "suggested_tension": "sus2",
    "progression_match": null,
    "matched_chords": [],
    "genre": "EDM",
    "emotional_comment": "",
    "mode": "dorian"
  },
  {
    "offset": 4.0,
    "pitches": [
      "F3",
      "A3",
      "C4"
    ],
    "q_length": 4.0,
    "style": "コードストローク",
    "section": "Verse 1",
    "chord_label": "",
    "velocity_base": 65,
    "humanize_style": "soft",
    "instrument_hint": "guitar",
    "is_fill": false,
    "emotional_description": "静けさ・記憶の霧",
    "suggested_tension": "sus2",
    "progression_match": null,
    "matched_chords": [],
    "genre": "EDM",
    "emotional_comment": "",
    "mode": "dorian"
  },
  {
    "offset": 8.0,
    "pitches": [
      "G3",
      "B3",
      "D4"
    ],
    "q_length": 4.0,
    "style": "コードストローク",
    "section": "Verse 1",
    "chord_label": "",
    "velocity_base": 65,
    "humanize_style": "soft",
    "instrument_hint": "guitar",
    "is_fill": false,
    "emotional_description": "静けさ・記憶の霧",
    "suggested_tension": "sus2",
    "progression_match": null,
    "matched_chords": [],
    "genre": "EDM",
    "emotional_comment": "",
    "mode": "dorian"
  },
  {
    "offset": 12.0,
    "pitches": [
      "Am3",
      "C4",
      "E4"
    ],
    "q_length": 4.0,
    "style": "コードストローク",
    "section": "Verse 1",
    "chord_label": "",
    "velocity_base": 65,
    "humanize_style": "soft",
    "instrument_hint": "guitar",
    "is_fill": false,
    "emotional_description": "静けさ・記憶の霧",
    "suggested_tension": "sus2",
    "progression_match": null,
    "matched_chords": [],
    "genre": "EDM",
    "emotional_comment": "",
    "mode": "dorian"
  },
  {
    "offset": 16.0,
    "pitches": [
      "C3",
      "E3",
      "G3"
    ],
    "q_length": 4.0,
    "style": "コードストローク",
    "section": "Verse 1",
    "chord_label": "",
    "velocity_base": 65,
    "humanize_style": "soft",
    "instrument_hint": "guitar",
    "is_fill": false,
    "emotional_description": "静けさ・記憶の霧",
    "suggested_tension": "sus2",
    "progression_match": null,
    "matched_chords": [],
    "genre": "EDM",
    "emotional_comment": "",
    "mode": "dorian"
  },
  {
    "offset": 20.0,
    "pitches": [
      "F3",
      "A3",
      "C4"
    ],
    "q_length": 4.0,
    "style": "コードストローク",
    "section": "Verse 1",
    "chord_label": "",
    "velocity_base": 65,
    "humanize_style": "soft",
    "instrument_hint": "guitar",
    "is_fill": false,
    "emotional_description": "静けさ・記憶の霧",
    "suggested_tension": "sus2",
    "progression_match": null,
    "matched_chords": [],
    "genre": "EDM",
    "emotional_comment": "",
    "mode": "dorian"
  },
  {
    "offset": 24.0,
    "pitches": [
      "G3",
      "B3",
      "D4"
    ],
    "q_length": 4.0,
    "style": "コードストローク",
    "section": "Verse 1",
    "chord_label": "",
    "velocity_base": 65,
    "humanize_style": "soft",
    "instrument_hint": "guitar",
    "is_fill": false,
    "emotional_description": "静けさ・記憶の霧",
    "suggested_tension": "sus2",
    "progression_match": null,
    "matched_chords": [],
    "genre": "EDM",
    "emotional_comment": "",
    "mode": "dorian"
  },
  {
    "offset": 28.0,
    "pitches": [
      "Am3",
      "C4",
      "E4"
    ],
    "q_length": 4.0,
    "style": "コードストローク",
    "section": "Verse 1",
    "chord_label": "",
    "velocity_base": 65,
    "humanize_style": "soft",
    "instrument_hint": "guitar",
    "is_fill": false,
    "emotional_description": "静けさ・記憶の霧",
    "suggested_tension": "sus2",
    "progression_match": null,
    "matched_chords": [],
    "genre": "EDM",
    "emotional_comment": "",
    "mode": "dorian"
  },
  {
    "offset": 32.0,
    "pitches": [
      "C3",
      "E3",
      "G3"
    ],
    "q_length": 4.0,
    "style": "コードストローク",
    "section": "Pre-Chorus 1",
    "chord_label": "",
    "velocity_base": 65,
    "humanize_style": "soft",
    "instrument_hint": "piano",
    "is_fill": false,
    "emotional_description": "深い後悔と元された思い",
    "suggested_tension": "m7,add11,13th",
    "progression_match": null,
    "matched_chords": [],
    "genre": "EDM",
    "emotional_comment": "",
    "mode": "aeolian"
  },
  {
    "offset": 36.0,
    "pitches": [
      "F3",
      "A3",
      "C4"
    ],
    "q_length": 4.0,
    "style": "コードストローク",
    "section": "Pre-Chorus 1",
    "chord_label": "",
    "velocity_base": 65,
    "humanize_style": "soft",
    "instrument_hint": "piano",
    "is_fill": false,
    "emotional_description": "深い後悔と元された思い",
    "suggested_tension": "m7,add11,13th",
    "progression_match": null,
    "matched_chords": [],
    "genre": "EDM",
    "emotional_comment": "",
    "mode": "aeolian"
  },
  {
    "offset": 40.0,
    "pitches": [
      "G3",
      "B3",
      "D4"
    ],
    "q_length": 4.0,
    "style": "コードストローク",
    "section": "Pre-Chorus 1",
    "chord_label": "",
    "velocity_base": 65,
    "humanize_style": "soft",
    "instrument_hint": "piano",
    "is_fill": false,
    "emotional_description": "深い後悔と元された思い",
    "suggested_tension": "m7,add11,13th",
    "progression_match": null,
    "matched_chords": [],
    "genre": "EDM",
    "emotional_comment": "",
    "mode": "aeolian"
  },
  {
    "offset": 44.0,
    "pitches": [
      "Am3",
      "C4",
      "E4"
    ],
    "q_length": 4.0,
    "style": "コードストローク",
    "section": "Pre-Chorus 1",
    "chord_label": "",
    "velocity_base": 65,
    "humanize_style": "soft",
    "instrument_hint": "piano",
    "is_fill": false,
    "emotional_description": "深い後悔と元された思い",
    "suggested_tension": "m7,add11,13th",
    "progression_match": null,
    "matched_chords": [],
    "genre": "EDM",
    "emotional_comment": "",
    "mode": "aeolian"
  },
  {
    "offset": 48.0,
    "pitches": [
      "C3",
      "E3",
      "G3"
    ],
    "q_length": 4.0,
    "style": "コードストローク",
    "section": "Pre-Chorus 1",
    "chord_label": "",
    "velocity_base": 65,
    "humanize_style": "soft",
    "instrument_hint": "piano",
    "is_fill": false,
    "emotional_description": "深い後悔と元された思い",
    "suggested_tension": "m7,add11,13th",
    "progression_match": null,
    "matched_chords": [],
    "genre": "EDM",
    "emotional_comment": "",
    "mode": "aeolian"
  },
  {
    "offset": 52.0,
    "pitches": [
      "F3",
      "A3",
      "C4"
    ],
    "q_length": 4.0,
    "style": "コードストローク",
    "section": "Pre-Chorus 1",
    "chord_label": "",
    "velocity_base": 65,
    "humanize_style": "soft",
    "instrument_hint": "piano",
    "is_fill": false,
    "emotional_description": "深い後悔と元された思い",
    "suggested_tension": "m7,add11,13th",
    "progression_match": null,
    "matched_chords": [],
    "genre": "EDM",
    "emotional_comment": "",
    "mode": "aeolian"
  },
  {
    "offset": 56.0,
    "pitches": [
      "G3",
      "B3",
      "D4"
    ],
    "q_length": 4.0,
    "style": "コードストローク",
    "section": "Pre-Chorus 1",
    "chord_label": "",
    "velocity_base": 65,
    "humanize_style": "soft",
    "instrument_hint": "piano",
    "is_fill": false,
    "emotional_description": "深い後悔と元された思い",
    "suggested_tension": "m7,add11,13th",
    "progression_match": null,
    "matched_chords": [],
    "genre": "EDM",
    "emotional_comment": "",
    "mode": "aeolian"
  },
  {
    "offset": 60.0,
    "pitches": [
      "Am3",
      "C4",
      "E4"
    ],
    "q_length": 4.0,
    "style": "コードストローク",
    "section": "Pre-Chorus 1",
    "chord_label": "",
    "velocity_base": 65,
    "humanize_style": "soft",
    "instrument_hint": "piano",
    "is_fill": false,
    "emotional_description": "深い後悔と元された思い",
    "suggested_tension": "m7,add11,13th",
    "progression_match": null,
    "matched_chords": [],
    "genre": "EDM",
    "emotional_comment": "",
    "mode": "aeolian"
  },
  {
    "offset": 64.0,
    "pitches": [
      "C3",
      "E3",
      "G3"
    ],
    "q_length": 4.0,
    "style": "コードストローク",
    "section": "Pre-Chorus 1",
    "chord_label": "",
    "velocity_base": 65,
    "humanize_style": "soft",
    "instrument_hint": "piano",
    "is_fill": false,
    "emotional_description": "深い後悔と元された思い",
    "suggested_tension": "m7,add11,13th",
    "progression_match": null,
    "matched_chords": [],
    "genre": "EDM",
    "emotional_comment": "",
    "mode": "aeolian"
  },
  {
    "offset": 68.0,
    "pitches": [
      "F3",
      "A3",
      "C4"
    ],
    "q_length": 1.0,
    "style": "コードストローク",
    "section": "Pre-Chorus 1",
    "chord_label": "",
    "velocity_base": 65,
    "humanize_style": "soft",
    "instrument_hint": "piano",
    "is_fill": false,
    "emotional_description": "深い後悔と元された思い",
    "suggested_tension": "m7,add11,13th",
    "progression_match": null,
    "matched_chords": [],
    "genre": "EDM",
    "emotional_comment": "",
    "mode": "aeolian"
  },
  {
    "offset": 69.0,
    "pitches": [
      "C3",
      "E3",
      "G3"
    ],
    "q_length": 4.0,
    "style": "コードストローク",
    "section": "Chorus 1",
    "chord_label": "",
    "velocity_base": 65,
    "humanize_style": "soft",
    "instrument_hint": "guitar+piano",
    "is_fill": false,
    "emotional_description": "愛の中の痛みを受け入れる",
    "suggested_tension": "add9,M7",
    "progression_match": null,
    "matched_chords": [],
    "genre": "EDM",
    "emotional_comment": "",
    "mode": "ionian"
  },
  {
    "offset": 73.0,
    "pitches": [
      "F3",
      "A3",
      "C4"
    ],
    "q_length": 4.0,
    "style": "コードストローク",
    "section": "Chorus 1",
    "chord_label": "",
    "velocity_base": 65,
    "humanize_style": "soft",
    "instrument_hint": "guitar+piano",
    "is_fill": false,
    "emotional_description": "愛の中の痛みを受け入れる",
    "suggested_tension": "add9,M7",
    "progression_match": null,
    "matched_chords": [],
    "genre": "EDM",
    "emotional_comment": "",
    "mode": "ionian"
  },
  {
    "offset": 77.0,
    "pitches": [
      "G3",
      "B3",
      "D4"
    ],
    "q_length": 4.0,
    "style": "コードストローク",
    "section": "Chorus 1",
    "chord_label": "",
    "velocity_base": 65,
    "humanize_style": "soft",
    "instrument_hint": "guitar+piano",
    "is_fill": false,
    "emotional_description": "愛の中の痛みを受け入れる",
    "suggested_tension": "add9,M7",
    "progression_match": null,
    "matched_chords": [],
    "genre": "EDM",
    "emotional_comment": "",
    "mode": "ionian"
  },
  {
    "offset": 81.0,
    "pitches": [
      "Am3",
      "C4",
      "E4"
    ],
    "q_length": 4.0,
    "style": "コードストローク",
    "section": "Chorus 1",
    "chord_label": "",
    "velocity_base": 65,
    "humanize_style": "soft",
    "instrument_hint": "guitar+piano",
    "is_fill": false,
    "emotional_description": "愛の中の痛みを受け入れる",
    "suggested_tension": "add9,M7",
    "progression_match": null,
    "matched_chords": [],
    "genre": "EDM",
    "emotional_comment": "",
    "mode": "ionian"
  },
  {
    "offset": 85.0,
    "pitches": [
      "C3",
      "E3",
      "G3"
    ],
    "q_length": 4.0,
    "style": "コードストローク",
    "section": "Chorus 1",
    "chord_label": "",
    "velocity_base": 65,
    "humanize_style": "soft",
    "instrument_hint": "guitar+piano",
    "is_fill": false,
    "emotional_description": "愛の中の痛みを受け入れる",
    "suggested_tension": "add9,M7",
    "progression_match": null,
    "matched_chords": [],
    "genre": "EDM",
    "emotional_comment": "",
    "mode": "ionian"
  },
  {
    "offset": 89.0,
    "pitches": [
      "F3",
      "A3",
      "C4"
    ],
    "q_length": 4.0,
    "style": "コードストローク",
    "section": "Chorus 1",
    "chord_label": "",
    "velocity_base": 65,
    "humanize_style": "soft",
    "instrument_hint": "guitar+piano",
    "is_fill": false,
    "emotional_description": "愛の中の痛みを受け入れる",
    "suggested_tension": "add9,M7",
    "progression_match": null,
    "matched_chords": [],
    "genre": "EDM",
    "emotional_comment": "",
    "mode": "ionian"
  },
  {
    "offset": 93.0,
    "pitches": [
      "G3",
      "B3",
      "D4"
    ],
    "q_length": 4.0,
    "style": "コードストローク",
    "section": "Chorus 1",
    "chord_label": "",
    "velocity_base": 65,
    "humanize_style": "soft",
    "instrument_hint": "guitar+piano",
    "is_fill": false,
    "emotional_description": "愛の中の痛みを受け入れる",
    "suggested_tension": "add9,M7",
    "progression_match": null,
    "matched_chords": [],
    "genre": "EDM",
    "emotional_comment": "",
    "mode": "ionian"
  },
  {
    "offset": 97.0,
    "pitches": [
      "Am3",
      "C4",
      "E4"
    ],
    "q_length": 4.0,
    "style": "コードストローク",
    "section": "Chorus 1",
    "chord_label": "",
    "velocity_base": 65,
    "humanize_style": "soft",
    "instrument_hint": "guitar+piano",
    "is_fill": false,
    "emotional_description": "愛の中の痛みを受け入れる",
    "suggested_tension": "add9,M7",
    "progression_match": null,
    "matched_chords": [],
    "genre": "EDM",
    "emotional_comment": "",
    "mode": "ionian"
  },
  {
    "offset": 101.0,
    "pitches": [
      "C3",
      "E3",
      "G3"
    ],
    "q_length": 4.0,
    "style": "コードストローク",
    "section": "Chorus 1",
    "chord_label": "",
    "velocity_base": 65,
    "humanize_style": "soft",
    "instrument_hint": "guitar+piano",
    "is_fill": false,
    "emotional_description": "愛の中の痛みを受け入れる",
    "suggested_tension": "add9,M7",
    "progression_match": null,
    "matched_chords": [],
    "genre": "EDM",
    "emotional_comment": "",
    "mode": "ionian"
  },
  {
    "offset": 105.0,
    "pitches": [
      "F3",
      "A3",
      "C4"
    ],
    "q_length": 4.0,
    "style": "コードストローク",
    "section": "Chorus 1",
    "chord_label": "",
    "velocity_base": 65,
    "humanize_style": "soft",
    "instrument_hint": "guitar+piano",
    "is_fill": false,
    "emotional_description": "愛の中の痛みを受け入れる",
    "suggested_tension": "add9,M7",
    "progression_match": null,
    "matched_chords": [],
    "genre": "EDM",
    "emotional_comment": "",
    "mode": "ionian"
  },
  {
    "offset": 109.0,
    "pitches": [
      "G3",
      "B3",
      "D4"
    ],
    "q_length": 4.0,
    "style": "コードストローク",
    "section": "Chorus 1",
    "chord_label": "",
    "velocity_base": 65,
    "humanize_style": "soft",
    "instrument_hint": "guitar+piano",
    "is_fill": false,
    "emotional_description": "愛の中の痛みを受け入れる",
    "suggested_tension": "add9,M7",
    "progression_match": null,
    "matched_chords": [],
    "genre": "EDM",
    "emotional_comment": "",
    "mode": "ionian"
  },
  {
    "offset": 113.0,
    "pitches": [
      "Am3",
      "C4",
      "E4"
    ],
    "q_length": 4.0,
    "style": "コードストローク",
    "section": "Chorus 1",
    "chord_label": "",
    "velocity_base": 65,
    "humanize_style": "soft",
    "instrument_hint": "guitar+piano",
    "is_fill": false,
    "emotional_description": "愛の中の痛みを受け入れる",
    "suggested_tension": "add9,M7",
    "progression_match": null,
    "matched_chords": [],
    "genre": "EDM",
    "emotional_comment": "",
    "mode": "ionian"
  },
  {
    "offset": 117.0,
    "pitches": [
      "C3",
      "E3",
      "G3"
    ],
    "q_length": 4.0,
    "style": "コードストローク",
    "section": "Chorus 1",
    "chord_label": "",
    "velocity_base": 65,
    "humanize_style": "soft",
    "instrument_hint": "guitar+piano",
    "is_fill": false,
    "emotional_description": "愛の中の痛みを受け入れる",
    "suggested_tension": "add9,M7",
    "progression_match": null,
    "matched_chords": [],
    "genre": "EDM",
    "emotional_comment": "",
    "mode": "ionian"
  },
  {
    "offset": 121.0,
    "pitches": [
      "F3",
      "A3",
      "C4"
    ],
    "q_length": 4.0,
    "style": "コードストローク",
    "section": "Chorus 1",
    "chord_label": "",
    "velocity_base": 65,
    "humanize_style": "soft",
    "instrument_hint": "guitar+piano",
    "is_fill": false,
    "emotional_description": "愛の中の痛みを受け入れる",
    "suggested_tension": "add9,M7",
    "progression_match": null,
    "matched_chords": [],
    "genre": "EDM",
    "emotional_comment": "",
    "mode": "ionian"
  },
  {
    "offset": 125.0,
    "pitches": [
      "G3",
      "B3",
      "D4"
    ],
    "q_length": 4.0,
    "style": "コードストローク",
    "section": "Chorus 1",
    "chord_label": "",
    "velocity_base": 65,
    "humanize_style": "soft",
    "instrument_hint": "guitar+piano",
    "is_fill": false,
    "emotional_description": "愛の中の痛みを受け入れる",
    "suggested_tension": "add9,M7",
    "progression_match": null,
    "matched_chords": [],
    "genre": "EDM",
    "emotional_comment": "",
    "mode": "ionian"
  },
  {
    "offset": 129.0,
    "pitches": [
      "Am3",
      "C4",
      "E4"
    ],
    "q_length": 4.0,
    "style": "コードストローク",
    "section": "Chorus 1",
    "chord_label": "",
    "velocity_base": 65,
    "humanize_style": "soft",
    "instrument_hint": "guitar+piano",
    "is_fill": false,
    "emotional_description": "愛の中の痛みを受け入れる",
    "suggested_tension": "add9,M7",
    "progression_match": null,
    "matched_chords": [],
    "genre": "EDM",
    "emotional_comment": "",
    "mode": "ionian"
  },
  {
    "offset": 133.0,
    "pitches": [
      "C3",
      "E3",
      "G3"
    ],
    "q_length": 4.0,
    "style": "コードストローク",
    "section": "Chorus 1",
    "chord_label": "",
    "velocity_base": 65,
    "humanize_style": "soft",
    "instrument_hint": "guitar+piano",
    "is_fill": false,
    "emotional_description": "愛の中の痛みを受け入れる",
    "suggested_tension": "add9,M7",
    "progression_match": null,
    "matched_chords": [],
    "genre": "EDM",
    "emotional_comment": "",
    "mode": "ionian"
  },
  {
    "offset": 137.0,
    "pitches": [
      "F3",
      "A3",
      "C4"
    ],
    "q_length": 4.0,
    "style": "コードストローク",
    "section": "Chorus 1",
    "chord_label": "",
    "velocity_base": 65,
    "humanize_style": "soft",
    "instrument_hint": "guitar+piano",
    "is_fill": false,
    "emotional_description": "愛の中の痛みを受け入れる",
    "suggested_tension": "add9,M7",
    "progression_match": null,
    "matched_chords": [],
    "genre": "EDM",
    "emotional_comment": "",
    "mode": "ionian"
  },
  {
    "offset": 141.0,
    "pitches": [
      "G3",
      "B3",
      "D4"
    ],
    "q_length": 4.0,
    "style": "コードストローク",
    "section": "Chorus 1",
    "chord_label": "",
    "velocity_base": 65,
    "humanize_style": "soft",
    "instrument_hint": "guitar+piano",
    "is_fill": false,
    "emotional_description": "愛の中の痛みを受け入れる",
    "suggested_tension": "add9,M7",
    "progression_match": null,
    "matched_chords": [],
    "genre": "EDM",
    "emotional_comment": "",
    "mode": "ionian"
  },
  {
    "offset": 145.0,
    "pitches": [
      "Am3",
      "C4",
      "E4"
    ],
    "q_length": 1.0,
    "style": "コードストローク",
    "section": "Chorus 1",
    "chord_label": "",
    "velocity_base": 65,
    "humanize_style": "soft",
    "instrument_hint": "guitar+piano",
    "is_fill": false,
    "emotional_description": "愛の中の痛みを受け入れる",
    "suggested_tension": "add9,M7",
    "progression_match": null,
    "matched_chords": [],
    "genre": "EDM",
    "emotional_comment": "",
    "mode": "ionian"
  },
  {
    "offset": 146.0,
    "pitches": [
      "C3",
      "E3",
      "G3"
    ],
    "q_length": 4.0,
    "style": "コードストローク",
    "section": "Verse 2",
    "chord_label": "",
    "velocity_base": 65,
    "humanize_style": "soft",
    "instrument_hint": "guitar",
    "is_fill": false,
    "emotional_description": "生の後悔と元された思い",
    "suggested_tension": "m7",
    "progression_match": null,
    "matched_chords": [],
    "genre": "EDM",
    "emotional_comment": "",
    "mode": "phrygian"
  },
  {
    "offset": 150.0,
    "pitches": [
      "F3",
      "A3",
      "C4"
    ],
    "q_length": 4.0,
    "style": "コードストローク",
    "section": "Verse 2",
    "chord_label": "",
    "velocity_base": 65,
    "humanize_style": "soft",
    "instrument_hint": "guitar",
    "is_fill": false,
    "emotional_description": "生の後悔と元された思い",
    "suggested_tension": "m7",
    "progression_match": null,
    "matched_chords": [],
    "genre": "EDM",
    "emotional_comment": "",
    "mode": "phrygian"
  },
  {
    "offset": 154.0,
    "pitches": [
      "G3",
      "B3",
      "D4"
    ],
    "q_length": 4.0,
    "style": "コードストローク",
    "section": "Verse 2",
    "chord_label": "",
    "velocity_base": 65,
    "humanize_style": "soft",
    "instrument_hint": "guitar",
    "is_fill": false,
    "emotional_description": "生の後悔と元された思い",
    "suggested_tension": "m7",
    "progression_match": null,
    "matched_chords": [],
    "genre": "EDM",
    "emotional_comment": "",
    "mode": "phrygian"
  },
  {
    "offset": 158.0,
    "pitches": [
      "Am3",
      "C4",
      "E4"
    ],
    "q_length": 4.0,
    "style": "コードストローク",
    "section": "Verse 2",
    "chord_label": "",
    "velocity_base": 65,
    "humanize_style": "soft",
    "instrument_hint": "guitar",
    "is_fill": false,
    "emotional_description": "生の後悔と元された思い",
    "suggested_tension": "m7",
    "progression_match": null,
    "matched_chords": [],
    "genre": "EDM",
    "emotional_comment": "",
    "mode": "phrygian"
  },
  {
    "offset": 162.0,
    "pitches": [
      "C3",
      "E3",
      "G3"
    ],
    "q_length": 4.0,
    "style": "コードストローク",
    "section": "Verse 2",
    "chord_label": "",
    "velocity_base": 65,
    "humanize_style": "soft",
    "instrument_hint": "guitar",
    "is_fill": false,
    "emotional_description": "生の後悔と元された思い",
    "suggested_tension": "m7",
    "progression_match": null,
    "matched_chords": [],
    "genre": "EDM",
    "emotional_comment": "",
    "mode": "phrygian"
  },
  {
    "offset": 166.0,
    "pitches": [
      "F3",
      "A3",
      "C4"
    ],
    "q_length": 4.0,
    "style": "コードストローク",
    "section": "Verse 2",
    "chord_label": "",
    "velocity_base": 65,
    "humanize_style": "soft",
    "instrument_hint": "guitar",
    "is_fill": false,
    "emotional_description": "生の後悔と元された思い",
    "suggested_tension": "m7",
    "progression_match": null,
    "matched_chords": [],
    "genre": "EDM",
    "emotional_comment": "",
    "mode": "phrygian"
  },
  {
    "offset": 170.0,
    "pitches": [
      "G3",
      "B3",
      "D4"
    ],
    "q_length": 4.0,
    "style": "コードストローク",
    "section": "Verse 2",
    "chord_label": "",
    "velocity_base": 65,
    "humanize_style": "soft",
    "instrument_hint": "guitar",
    "is_fill": false,
    "emotional_description": "生の後悔と元された思い",
    "suggested_tension": "m7",
    "progression_match": null,
    "matched_chords": [],
    "genre": "EDM",
    "emotional_comment": "",
    "mode": "phrygian"
  },
  {
    "offset": 174.0,
    "pitches": [
      "Am3",
      "C4",
      "E4"
    ],
    "q_length": 4.0,
    "style": "コードストローク",
    "section": "Verse 2",
    "chord_label": "",
    "velocity_base": 65,
    "humanize_style": "soft",
    "instrument_hint": "guitar",
    "is_fill": false,
    "emotional_description": "生の後悔と元された思い",
    "suggested_tension": "m7",
    "progression_match": null,
    "matched_chords": [],
    "genre": "EDM",
    "emotional_comment": "",
    "mode": "phrygian"
  },
  {
    "offset": 178.0,
    "pitches": [
      "C3",
      "E3",
      "G3"
    ],
    "q_length": 4.0,
    "style": "コードストローク",
    "section": "Verse 2",
    "chord_label": "",
    "velocity_base": 65,
    "humanize_style": "soft",
    "instrument_hint": "guitar",
    "is_fill": false,
    "emotional_description": "生の後悔と元された思い",
    "suggested_tension": "m7",
    "progression_match": null,
    "matched_chords": [],
    "genre": "EDM",
    "emotional_comment": "",
    "mode": "phrygian"
  },
  {
    "offset": 182.0,
    "pitches": [
      "F3",
      "A3",
      "C4"
    ],
    "q_length": 4.0,
    "style": "コードストローク",
    "section": "Verse 2",
    "chord_label": "",
    "velocity_base": 65,
    "humanize_style": "soft",
    "instrument_hint": "guitar",
    "is_fill": false,
    "emotional_description": "生の後悔と元された思い",
    "suggested_tension": "m7",
    "progression_match": null,
    "matched_chords": [],
    "genre": "EDM",
    "emotional_comment": "",
    "mode": "phrygian"
  },
  {
    "offset": 186.0,
    "pitches": [
      "G3",
      "B3",
      "D4"
    ],
    "q_length": 4.0,
    "style": "コードストローク",
    "section": "Verse 2",
    "chord_label": "",
    "velocity_base": 65,
    "humanize_style": "soft",
    "instrument_hint": "guitar",
    "is_fill": false,
    "emotional_description": "生の後悔と元された思い",
    "suggested_tension": "m7",
    "progression_match": null,
    "matched_chords": [],
    "genre": "EDM",
    "emotional_comment": "",
    "mode": "phrygian"
  },
  {
    "offset": 190.0,
    "pitches": [
      "Am3",
      "C4",
      "E4"
    ],
    "q_length": 4.0,
    "style": "コードストローク",
    "section": "Verse 2",
    "chord_label": "",
    "velocity_base": 65,
    "humanize_style": "soft",
    "instrument_hint": "guitar",
    "is_fill": false,
    "emotional_description": "生の後悔と元された思い",
    "suggested_tension": "m7",
    "progression_match": null,
    "matched_chords": [],
    "genre": "EDM",
    "emotional_comment": "",
    "mode": "phrygian"
  },
  {
    "offset": 194.0,
    "pitches": [
      "C3",
      "E3",
      "G3"
    ],
    "q_length": 4.0,
    "style": "コードストローク",
    "section": "Verse 2",
    "chord_label": "",
    "velocity_base": 65,
    "humanize_style": "soft",
    "instrument_hint": "guitar",
    "is_fill": false,
    "emotional_description": "生の後悔と元された思い",
    "suggested_tension": "m7",
    "progression_match": null,
    "matched_chords": [],
    "genre": "EDM",
    "emotional_comment": "",
    "mode": "phrygian"
  },
  {
    "offset": 198.0,
    "pitches": [
      "F3",
      "A3",
      "C4"
    ],
    "q_length": 4.0,
    "style": "コードストローク",
    "section": "Verse 2",
    "chord_label": "",
    "velocity_base": 65,
    "humanize_style": "soft",
    "instrument_hint": "guitar",
    "is_fill": false,
    "emotional_description": "生の後悔と元された思い",
    "suggested_tension": "m7",
    "progression_match": null,
    "matched_chords": [],
    "genre": "EDM",
    "emotional_comment": "",
    "mode": "phrygian"
  },
  {
    "offset": 202.0,
    "pitches": [
      "G3",
      "B3",
      "D4"
    ],
    "q_length": 4.0,
    "style": "コードストローク",
    "section": "Verse 2",
    "chord_label": "",
    "velocity_base": 65,
    "humanize_style": "soft",
    "instrument_hint": "guitar",
    "is_fill": false,
    "emotional_description": "生の後悔と元された思い",
    "suggested_tension": "m7",
    "progression_match": null,
    "matched_chords": [],
    "genre": "EDM",
    "emotional_comment": "",
    "mode": "phrygian"
  },
  {
    "offset": 206.0,
    "pitches": [
      "Am3",
      "C4",
      "E4"
    ],
    "q_length": 4.0,
    "style": "コードストローク",
    "section": "Verse 2",
    "chord_label": "",
    "velocity_base": 65,
    "humanize_style": "soft",
    "instrument_hint": "guitar",
    "is_fill": false,
    "emotional_description": "生の後悔と元された思い",
    "suggested_tension": "m7",
    "progression_match": null,
    "matched_chords": [],
    "genre": "EDM",
    "emotional_comment": "",
    "mode": "phrygian"
  },
  {
    "offset": 210.0,
    "pitches": [
      "C3",
      "E3",
      "G3"
    ],
    "q_length": 4.0,
    "style": "コードストローク",
    "section": "Verse 2",
    "chord_label": "",
    "velocity_base": 65,
    "humanize_style": "soft",
    "instrument_hint": "guitar",
    "is_fill": false,
    "emotional_description": "生の後悔と元された思い",
    "suggested_tension": "m7",
    "progression_match": null,
    "matched_chords": [],
    "genre": "EDM",
    "emotional_comment": "",
    "mode": "phrygian"
  },
  {
    "offset": 214.0,
    "pitches": [
      "F3",
      "A3",
      "C4"
    ],
    "q_length": 4.0,
    "style": "コードストローク",
    "section": "Verse 2",
    "chord_label": "",
    "velocity_base": 65,
    "humanize_style": "soft",
    "instrument_hint": "guitar",
    "is_fill": false,
    "emotional_description": "生の後悔と元された思い",
    "suggested_tension": "m7",
    "progression_match": null,
    "matched_chords": [],
    "genre": "EDM",
    "emotional_comment": "",
    "mode": "phrygian"
  },
  {
    "offset": 218.0,
    "pitches": [
      "G3",
      "B3",
      "D4"
    ],
    "q_length": 4.0,
    "style": "コードストローク",
    "section": "Verse 2",
    "chord_label": "",
    "velocity_base": 65,
    "humanize_style": "soft",
    "instrument_hint": "guitar",
    "is_fill": false,
    "emotional_description": "生の後悔と元された思い",
    "suggested_tension": "m7",
    "progression_match": null,
    "matched_chords": [],
    "genre": "EDM",
    "emotional_comment": "",
    "mode": "phrygian"
  },
  {
    "offset": 222.0,
    "pitches": [
      "Am3",
      "C4",
      "E4"
    ],
    "q_length": 4.0,
    "style": "コードストローク",
    "section": "Verse 2",
    "chord_label": "",
    "velocity_base": 65,
    "humanize_style": "soft",
    "instrument_hint": "guitar",
    "is_fill": false,
    "emotional_description": "生の後悔と元された思い",
    "suggested_tension": "m7",
    "progression_match": null,
    "matched_chords": [],
    "genre": "EDM",
    "emotional_comment": "",
    "mode": "phrygian"
  },
  {
    "offset": 226.0,
    "pitches": [
      "C3",
      "E3",
      "G3"
    ],
    "q_length": 4.0,
    "style": "コードストローク",
    "section": "Verse 2",
    "chord_label": "",
    "velocity_base": 65,
    "humanize_style": "soft",
    "instrument_hint": "guitar",
    "is_fill": false,
    "emotional_description": "生の後悔と元された思い",
    "suggested_tension": "m7",
    "progression_match": null,
    "matched_chords": [],
    "genre": "EDM",
    "emotional_comment": "",
    "mode": "phrygian"
  },
  {
    "offset": 230.0,
    "pitches": [
      "F3",
      "A3",
      "C4"
    ],
    "q_length": 4.0,
    "style": "コードストローク",
    "section": "Verse 2",
    "chord_label": "",
    "velocity_base": 65,
    "humanize_style": "soft",
    "instrument_hint": "guitar",
    "is_fill": false,
    "emotional_description": "生の後悔と元された思い",
    "suggested_tension": "m7",
    "progression_match": null,
    "matched_chords": [],
    "genre": "EDM",
    "emotional_comment": "",
    "mode": "phrygian"
  },
  {
    "offset": 234.0,
    "pitches": [
      "G3",
      "B3",
      "D4"
    ],
    "q_length": 4.0,
    "style": "コードストローク",
    "section": "Verse 2",
    "chord_label": "",
    "velocity_base": 65,
    "humanize_style": "soft",
    "instrument_hint": "guitar",
    "is_fill": false,
    "emotional_description": "生の後悔と元された思い",
    "suggested_tension": "m7",
    "progression_match": null,
    "matched_chords": [],
    "genre": "EDM",
    "emotional_comment": "",
    "mode": "phrygian"
  },
  {
    "offset": 238.0,
    "pitches": [
      "Am3",
      "C4",
      "E4"
    ],
    "q_length": 4.0,
    "style": "コードストローク",
    "section": "Verse 2",
    "chord_label": "",
    "velocity_base": 65,
    "humanize_style": "soft",
    "instrument_hint": "guitar",
    "is_fill": false,
    "emotional_description": "生の後悔と元された思い",
    "suggested_tension": "m7",
    "progression_match": null,
    "matched_chords": [],
    "genre": "EDM",
    "emotional_comment": "",
    "mode": "phrygian"
  },
  {
    "offset": 242.0,
    "pitches": [
      "C3",
      "E3",
      "G3"
    ],
    "q_length": 4.0,
    "style": "コードストローク",
    "section": "Verse 2",
    "chord_label": "",
    "velocity_base": 65,
    "humanize_style": "soft",
    "instrument_hint": "guitar",
    "is_fill": false,
    "emotional_description": "生の後悔と元された思い",
    "suggested_tension": "m7",
    "progression_match": null,
    "matched_chords": [],
    "genre": "EDM",
    "emotional_comment": "",
    "mode": "phrygian"
  },
  {
    "offset": 246.0,
    "pitches": [
      "F3",
      "A3",
      "C4"
    ],
    "q_length": 4.0,
    "style": "コードストローク",
    "section": "Verse 2",
    "chord_label": "",
    "velocity_base": 65,
    "humanize_style": "soft",
    "instrument_hint": "guitar",
    "is_fill": false,
    "emotional_description": "生の後悔と元された思い",
    "suggested_tension": "m7",
    "progression_match": null,
    "matched_chords": [],
    "genre": "EDM",
    "emotional_comment": "",
    "mode": "phrygian"
  },
  {
    "offset": 250.0,
    "pitches": [
      "G3",
      "B3",
      "D4"
    ],
    "q_length": 4.0,
    "style": "コードストローク",
    "section": "Verse 2",
    "chord_label": "",
    "velocity_base": 65,
    "humanize_style": "soft",
    "instrument_hint": "guitar",
    "is_fill": false,
    "emotional_description": "生の後悔と元された思い",
    "suggested_tension": "m7",
    "progression_match": null,
    "matched_chords": [],
    "genre": "EDM",
    "emotional_comment": "",
    "mode": "phrygian"
  },
  {
    "offset": 254.0,
    "pitches": [
      "Am3",
      "C4",
      "E4"
    ],
    "q_length": 4.0,
    "style": "コードストローク",
    "section": "Verse 2",
    "chord_label": "",
    "velocity_base": 65,
    "humanize_style": "soft",
    "instrument_hint": "guitar",
    "is_fill": false,
    "emotional_description": "生の後悔と元された思い",
    "suggested_tension": "m7",
    "progression_match": null,
    "matched_chords": [],
    "genre": "EDM",
    "emotional_comment": "",
    "mode": "phrygian"
  },
  {
    "offset": 258.0,
    "pitches": [
      "C3",
      "E3",
      "G3"
    ],
    "q_length": 4.0,
    "style": "コードストローク",
    "section": "Chorus 2",
    "chord_label": "",
    "velocity_base": 65,
    "humanize_style": "soft",
    "instrument_hint": "piano",
    "is_fill": false,
    "emotional_description": "ほのかな望みの結び直し",
    "suggested_tension": "add13",
    "progression_match": null,
    "matched_chords": [],
    "genre": "EDM",
    "emotional_comment": "",
    "mode": "dorian"
  },
  {
    "offset": 262.0,
    "pitches": [
      "F3",
      "A3",
      "C4"
    ],
    "q_length": 4.0,
    "style": "コードストローク",
    "section": "Chorus 2",
    "chord_label": "",
    "velocity_base": 65,
    "humanize_style": "soft",
    "instrument_hint": "piano",
    "is_fill": false,
    "emotional_description": "ほのかな望みの結び直し",
    "suggested_tension": "add13",
    "progression_match": null,
    "matched_chords": [],
    "genre": "EDM",
    "emotional_comment": "",
    "mode": "dorian"
  },
  {
    "offset": 266.0,
    "pitches": [
      "G3",
      "B3",
      "D4"
    ],
    "q_length": 4.0,
    "style": "コードストローク",
    "section": "Chorus 2",
    "chord_label": "",
    "velocity_base": 65,
    "humanize_style": "soft",
    "instrument_hint": "piano",
    "is_fill": false,
    "emotional_description": "ほのかな望みの結び直し",
    "suggested_tension": "add13",
    "progression_match": null,
    "matched_chords": [],
    "genre": "EDM",
    "emotional_comment": "",
    "mode": "dorian"
  },
  {
    "offset": 270.0,
    "pitches": [
      "Am3",
      "C4",
      "E4"
    ],
    "q_length": 4.0,
    "style": "コードストローク",
    "section": "Chorus 2",
    "chord_label": "",
    "velocity_base": 65,
    "humanize_style": "soft",
    "instrument_hint": "piano",
    "is_fill": false,
    "emotional_description": "ほのかな望みの結び直し",
    "suggested_tension": "add13",
    "progression_match": null,
    "matched_chords": [],
    "genre": "EDM",
    "emotional_comment": "",
    "mode": "dorian"
  },
  {
    "offset": 274.0,
    "pitches": [
      "C3",
      "E3",
      "G3"
    ],
    "q_length": 4.0,
    "style": "コードストローク",
    "section": "Chorus 2",
    "chord_label": "",
    "velocity_base": 65,
    "humanize_style": "soft",
    "instrument_hint": "piano",
    "is_fill": false,
    "emotional_description": "ほのかな望みの結び直し",
    "suggested_tension": "add13",
    "progression_match": null,
    "matched_chords": [],
    "genre": "EDM",
    "emotional_comment": "",
    "mode": "dorian"
  },
  {
    "offset": 278.0,
    "pitches": [
      "F3",
      "A3",
      "C4"
    ],
    "q_length": 4.0,
    "style": "コードストローク",
    "section": "Chorus 2",
    "chord_label": "",
    "velocity_base": 65,
    "humanize_style": "soft",
    "instrument_hint": "piano",
    "is_fill": false,
    "emotional_description": "ほのかな望みの結び直し",
    "suggested_tension": "add13",
    "progression_match": null,
    "matched_chords": [],
    "genre": "EDM",
    "emotional_comment": "",
    "mode": "dorian"
  },
  {
    "offset": 282.0,
    "pitches": [
      "C3",
      "E3",
      "G3"
    ],
    "q_length": 4.0,
    "style": "コードストローク",
    "section": "Bridge 1",
    "chord_label": "",
    "velocity_base": 65,
    "humanize_style": "soft",
    "instrument_hint": "subbass+piano",
    "is_fill": false,
    "emotional_description": "内面の強い争いと認知",
    "suggested_tension": "low11th,add13",
    "progression_match": null,
    "matched_chords": [],
    "genre": "EDM",
    "emotional_comment": "",
    "mode": "mixolydian"
  },
  {
    "offset": 286.0,
    "pitches": [
      "F3",
      "A3",
      "C4"
    ],
    "q_length": 4.0,
    "style": "コードストローク",
    "section": "Bridge 1",
    "chord_label": "",
    "velocity_base": 65,
    "humanize_style": "soft",
    "instrument_hint": "subbass+piano",
    "is_fill": false,
    "emotional_description": "内面の強い争いと認知",
    "suggested_tension": "low11th,add13",
    "progression_match": null,
    "matched_chords": [],
    "genre": "EDM",
    "emotional_comment": "",
    "mode": "mixolydian"
  },
  {
    "offset": 290.0,
    "pitches": [
      "G3",
      "B3",
      "D4"
    ],
    "q_length": 4.0,
    "style": "コードストローク",
    "section": "Bridge 1",
    "chord_label": "",
    "velocity_base": 65,
    "humanize_style": "soft",
    "instrument_hint": "subbass+piano",
    "is_fill": false,
    "emotional_description": "内面の強い争いと認知",
    "suggested_tension": "low11th,add13",
    "progression_match": null,
    "matched_chords": [],
    "genre": "EDM",
    "emotional_comment": "",
    "mode": "mixolydian"
  },
  {
    "offset": 294.0,
    "pitches": [
      "Am3",
      "C4",
      "E4"
    ],
    "q_length": 4.0,
    "style": "コードストローク",
    "section": "Bridge 1",
    "chord_label": "",
    "velocity_base": 65,
    "humanize_style": "soft",
    "instrument_hint": "subbass+piano",
    "is_fill": false,
    "emotional_description": "内面の強い争いと認知",
    "suggested_tension": "low11th,add13",
    "progression_match": null,
    "matched_chords": [],
    "genre": "EDM",
    "emotional_comment": "",
    "mode": "mixolydian"
  },
  {
    "offset": 298.0,
    "pitches": [
      "C3",
      "E3",
      "G3"
    ],
    "q_length": 4.0,
    "style": "コードストローク",
    "section": "Bridge 1",
    "chord_label": "",
    "velocity_base": 65,
    "humanize_style": "soft",
    "instrument_hint": "subbass+piano",
    "is_fill": false,
    "emotional_description": "内面の強い争いと認知",
    "suggested_tension": "low11th,add13",
    "progression_match": null,
    "matched_chords": [],
    "genre": "EDM",
    "emotional_comment": "",
    "mode": "mixolydian"
  },
  {
    "offset": 302.0,
    "pitches": [
      "F3",
      "A3",
      "C4"
    ],
    "q_length": 4.0,
    "style": "コードストローク",
    "section": "Bridge 1",
    "chord_label": "",
    "velocity_base": 65,
    "humanize_style": "soft",
    "instrument_hint": "subbass+piano",
    "is_fill": false,
    "emotional_description": "内面の強い争いと認知",
    "suggested_tension": "low11th,add13",
    "progression_match": null,
    "matched_chords": [],
    "genre": "EDM",
    "emotional_comment": "",
    "mode": "mixolydian"
  },
  {
    "offset": 306.0,
    "pitches": [
      "G3",
      "B3",
      "D4"
    ],
    "q_length": 4.0,
    "style": "コードストローク",
    "section": "Bridge 1",
    "chord_label": "",
    "velocity_base": 65,
    "humanize_style": "soft",
    "instrument_hint": "subbass+piano",
    "is_fill": false,
    "emotional_description": "内面の強い争いと認知",
    "suggested_tension": "low11th,add13",
    "progression_match": null,
    "matched_chords": [],
    "genre": "EDM",
    "emotional_comment": "",
    "mode": "mixolydian"
  },
  {
    "offset": 310.0,
    "pitches": [
      "Am3",
      "C4",
      "E4"
    ],
    "q_length": 4.0,
    "style": "コードストローク",
    "section": "Bridge 1",
    "chord_label": "",
    "velocity_base": 65,
    "humanize_style": "soft",
    "instrument_hint": "subbass+piano",
    "is_fill": false,
    "emotional_description": "内面の強い争いと認知",
    "suggested_tension": "low11th,add13",
    "progression_match": null,
    "matched_chords": [],
    "genre": "EDM",
    "emotional_comment": "",
    "mode": "mixolydian"
  },
  {
    "offset": 314.0,
    "pitches": [
      "C3",
      "E3",
      "G3"
    ],
    "q_length": 4.0,
    "style": "コードストローク",
    "section": "Verse 3",
    "chord_label": "",
    "velocity_base": 65,
    "humanize_style": "soft",
    "instrument_hint": "guitar",
    "is_fill": false,
    "emotional_description": "忍んだ感情の回想",
    "suggested_tension": "sus2",
    "progression_match": null,
    "matched_chords": [],
    "genre": "EDM",
    "emotional_comment": "",
    "mode": "aeolian"
  },
  {
    "offset": 318.0,
    "pitches": [
      "F3",
      "A3",
      "C4"
    ],
    "q_length": 4.0,
    "style": "コードストローク",
    "section": "Verse 3",
    "chord_label": "",
    "velocity_base": 65,
    "humanize_style": "soft",
    "instrument_hint": "guitar",
    "is_fill": false,
    "emotional_description": "忍んだ感情の回想",
    "suggested_tension": "sus2",
    "progression_match": null,
    "matched_chords": [],
    "genre": "EDM",
    "emotional_comment": "",
    "mode": "aeolian"
  },
  {
    "offset": 322.0,
    "pitches": [
      "G3",
      "B3",
      "D4"
    ],
    "q_length": 4.0,
    "style": "コードストローク",
    "section": "Verse 3",
    "chord_label": "",
    "velocity_base": 65,
    "humanize_style": "soft",
    "instrument_hint": "guitar",
    "is_fill": false,
    "emotional_description": "忍んだ感情の回想",
    "suggested_tension": "sus2",
    "progression_match": null,
    "matched_chords": [],
    "genre": "EDM",
    "emotional_comment": "",
    "mode": "aeolian"
  },
  {
    "offset": 326.0,
    "pitches": [
      "Am3",
      "C4",
      "E4"
    ],
    "q_length": 4.0,
    "style": "コードストローク",
    "section": "Verse 3",
    "chord_label": "",
    "velocity_base": 65,
    "humanize_style": "soft",
    "instrument_hint": "guitar",
    "is_fill": false,
    "emotional_description": "忍んだ感情の回想",
    "suggested_tension": "sus2",
    "progression_match": null,
    "matched_chords": [],
    "genre": "EDM",
    "emotional_comment": "",
    "mode": "aeolian"
  },
  {
    "offset": 330.0,
    "pitches": [
      "C3",
      "E3",
      "G3"
    ],
    "q_length": 4.0,
    "style": "コードストローク",
    "section": "Verse 3",
    "chord_label": "",
    "velocity_base": 65,
    "humanize_style": "soft",
    "instrument_hint": "guitar",
    "is_fill": false,
    "emotional_description": "忍んだ感情の回想",
    "suggested_tension": "sus2",
    "progression_match": null,
    "matched_chords": [],
    "genre": "EDM",
    "emotional_comment": "",
    "mode": "aeolian"
  },
  {
    "offset": 334.0,
    "pitches": [
      "F3",
      "A3",
      "C4"
    ],
    "q_length": 4.0,
    "style": "コードストローク",
    "section": "Verse 3",
    "chord_label": "",
    "velocity_base": 65,
    "humanize_style": "soft",
    "instrument_hint": "guitar",
    "is_fill": false,
    "emotional_description": "忍んだ感情の回想",
    "suggested_tension": "sus2",
    "progression_match": null,
    "matched_chords": [],
    "genre": "EDM",
    "emotional_comment": "",
    "mode": "aeolian"
  },
  {
    "offset": 338.0,
    "pitches": [
      "G3",
      "B3",
      "D4"
    ],
    "q_length": 4.0,
    "style": "コードストローク",
    "section": "Verse 3",
    "chord_label": "",
    "velocity_base": 65,
    "humanize_style": "soft",
    "instrument_hint": "guitar",
    "is_fill": false,
    "emotional_description": "忍んだ感情の回想",
    "suggested_tension": "sus2",
    "progression_match": null,
    "matched_chords": [],
    "genre": "EDM",
    "emotional_comment": "",
    "mode": "aeolian"
  },
  {
    "offset": 342.0,
    "pitches": [
      "Am3",
      "C4",
      "E4"
    ],
    "q_length": 4.0,
    "style": "コードストローク",
    "section": "Verse 3",
    "chord_label": "",
    "velocity_base": 65,
    "humanize_style": "soft",
    "instrument_hint": "guitar",
    "is_fill": false,
    "emotional_description": "忍んだ感情の回想",
    "suggested_tension": "sus2",
    "progression_match": null,
    "matched_chords": [],
    "genre": "EDM",
    "emotional_comment": "",
    "mode": "aeolian"
  },
  {
    "offset": 346.0,
    "pitches": [
      "C3",
      "E3",
      "G3"
    ],
    "q_length": 4.0,
    "style": "コードストローク",
    "section": "Pre-Chorus 2",
    "chord_label": "",
    "velocity_base": 65,
    "humanize_style": "soft",
    "instrument_hint": "piano",
    "is_fill": false,
    "emotional_description": "远回りの手を叩き合う",
    "suggested_tension": "m7,add11",
    "progression_match": null,
    "matched_chords": [],
    "genre": "EDM",
    "emotional_comment": "",
    "mode": "dorian"
  },
  {
    "offset": 350.0,
    "pitches": [
      "F3",
      "A3",
      "C4"
    ],
    "q_length": 4.0,
    "style": "コードストローク",
    "section": "Pre-Chorus 2",
    "chord_label": "",
    "velocity_base": 65,
    "humanize_style": "soft",
    "instrument_hint": "piano",
    "is_fill": false,
    "emotional_description": "远回りの手を叩き合う",
    "suggested_tension": "m7,add11",
    "progression_match": null,
    "matched_chords": [],
    "genre": "EDM",
    "emotional_comment": "",
    "mode": "dorian"
  },
  {
    "offset": 354.0,
    "pitches": [
      "G3",
      "B3",
      "D4"
    ],
    "q_length": 4.0,
    "style": "コードストローク",
    "section": "Pre-Chorus 2",
    "chord_label": "",
    "velocity_base": 65,
    "humanize_style": "soft",
    "instrument_hint": "piano",
    "is_fill": false,
    "emotional_description": "远回りの手を叩き合う",
    "suggested_tension": "m7,add11",
    "progression_match": null,
    "matched_chords": [],
    "genre": "EDM",
    "emotional_comment": "",
    "mode": "dorian"
  },
  {
    "offset": 358.0,
    "pitches": [
      "Am3",
      "C4",
      "E4"
    ],
    "q_length": 4.0,
    "style": "コードストローク",
    "section": "Pre-Chorus 2",
    "chord_label": "",
    "velocity_base": 65,
    "humanize_style": "soft",
    "instrument_hint": "piano",
    "is_fill": false,
    "emotional_description": "远回りの手を叩き合う",
    "suggested_tension": "m7,add11",
    "progression_match": null,
    "matched_chords": [],
    "genre": "EDM",
    "emotional_comment": "",
    "mode": "dorian"
  },
  {
    "offset": 362.0,
    "pitches": [
      "C3",
      "E3",
      "G3"
    ],
    "q_length": 4.0,
    "style": "コードストローク",
    "section": "Pre-Chorus 2",
    "chord_label": "",
    "velocity_base": 65,
    "humanize_style": "soft",
    "instrument_hint": "piano",
    "is_fill": false,
    "emotional_description": "远回りの手を叩き合う",
    "suggested_tension": "m7,add11",
    "progression_match": null,
    "matched_chords": [],
    "genre": "EDM",
    "emotional_comment": "",
    "mode": "dorian"
  },
  {
    "offset": 366.0,
    "pitches": [
      "F3",
      "A3",
      "C4"
    ],
    "q_length": 4.0,
    "style": "コードストローク",
    "section": "Pre-Chorus 2",
    "chord_label": "",
    "velocity_base": 65,
    "humanize_style": "soft",
    "instrument_hint": "piano",
    "is_fill": false,
    "emotional_description": "远回りの手を叩き合う",
    "suggested_tension": "m7,add11",
    "progression_match": null,
    "matched_chords": [],
    "genre": "EDM",
    "emotional_comment": "",
    "mode": "dorian"
  },
  {
    "offset": 370.0,
    "pitches": [
      "G3",
      "B3",
      "D4"
    ],
    "q_length": 4.0,
    "style": "コードストローク",
    "section": "Pre-Chorus 2",
    "chord_label": "",
    "velocity_base": 65,
    "humanize_style": "soft",
    "instrument_hint": "piano",
    "is_fill": false,
    "emotional_description": "远回りの手を叩き合う",
    "suggested_tension": "m7,add11",
    "progression_match": null,
    "matched_chords": [],
    "genre": "EDM",
    "emotional_comment": "",
    "mode": "dorian"
  },
  {
    "offset": 374.0,
    "pitches": [
      "Am3",
      "C4",
      "E4"
    ],
    "q_length": 4.0,
    "style": "コードストローク",
    "section": "Pre-Chorus 2",
    "chord_label": "",
    "velocity_base": 65,
    "humanize_style": "soft",
    "instrument_hint": "piano",
    "is_fill": false,
    "emotional_description": "远回りの手を叩き合う",
    "suggested_tension": "m7,add11",
    "progression_match": null,
    "matched_chords": [],
    "genre": "EDM",
    "emotional_comment": "",
    "mode": "dorian"
  },
  {
    "offset": 378.0,
    "pitches": [
      "C3",
      "E3",
      "G3"
    ],
    "q_length": 2.0,
    "style": "コードストローク",
    "section": "Pre-Chorus 2",
    "chord_label": "",
    "velocity_base": 65,
    "humanize_style": "soft",
    "instrument_hint": "piano",
    "is_fill": false,
    "emotional_description": "远回りの手を叩き合う",
    "suggested_tension": "m7,add11",
    "progression_match": null,
    "matched_chords": [],
    "genre": "EDM",
    "emotional_comment": "",
    "mode": "dorian"
  },
  {
    "offset": 380.0,
    "pitches": [
      "C3",
      "E3",
      "G3"
    ],
    "q_length": 4.0,
    "style": "コードストローク",
    "section": "Chorus 3",
    "chord_label": "",
    "velocity_base": 65,
    "humanize_style": "soft",
    "instrument_hint": "guitar+piano",
    "is_fill": false,
    "emotional_description": "前向きな決意",
    "suggested_tension": "add9,M7,13th",
    "progression_match": null,
    "matched_chords": [],
    "genre": "EDM",
    "emotional_comment": "",
    "mode": "ionian"
  },
  {
    "offset": 384.0,
    "pitches": [
      "F3",
      "A3",
      "C4"
    ],
    "q_length": 4.0,
    "style": "コードストローク",
    "section": "Chorus 3",
    "chord_label": "",
    "velocity_base": 65,
    "humanize_style": "soft",
    "instrument_hint": "guitar+piano",
    "is_fill": false,
    "emotional_description": "前向きな決意",
    "suggested_tension": "add9,M7,13th",
    "progression_match": null,
    "matched_chords": [],
    "genre": "EDM",
    "emotional_comment": "",
    "mode": "ionian"
  },
  {
    "offset": 388.0,
    "pitches": [
      "G3",
      "B3",
      "D4"
    ],
    "q_length": 4.0,
    "style": "コードストローク",
    "section": "Chorus 3",
    "chord_label": "",
    "velocity_base": 65,
    "humanize_style": "soft",
    "instrument_hint": "guitar+piano",
    "is_fill": false,
    "emotional_description": "前向きな決意",
    "suggested_tension": "add9,M7,13th",
    "progression_match": null,
    "matched_chords": [],
    "genre": "EDM",
    "emotional_comment": "",
    "mode": "ionian"
  },
  {
    "offset": 392.0,
    "pitches": [
      "Am3",
      "C4",
      "E4"
    ],
    "q_length": 4.0,
    "style": "コードストローク",
    "section": "Chorus 3",
    "chord_label": "",
    "velocity_base": 65,
    "humanize_style": "soft",
    "instrument_hint": "guitar+piano",
    "is_fill": false,
    "emotional_description": "前向きな決意",
    "suggested_tension": "add9,M7,13th",
    "progression_match": null,
    "matched_chords": [],
    "genre": "EDM",
    "emotional_comment": "",
    "mode": "ionian"
  },
  {
    "offset": 396.0,
    "pitches": [
      "C3",
      "E3",
      "G3"
    ],
    "q_length": 4.0,
    "style": "コードストローク",
    "section": "Chorus 3",
    "chord_label": "",
    "velocity_base": 65,
    "humanize_style": "soft",
    "instrument_hint": "guitar+piano",
    "is_fill": false,
    "emotional_description": "前向きな決意",
    "suggested_tension": "add9,M7,13th",
    "progression_match": null,
    "matched_chords": [],
    "genre": "EDM",
    "emotional_comment": "",
    "mode": "ionian"
  },
  {
    "offset": 400.0,
    "pitches": [
      "F3",
      "A3",
      "C4"
    ],
    "q_length": 4.0,
    "style": "コードストローク",
    "section": "Chorus 3",
    "chord_label": "",
    "velocity_base": 65,
    "humanize_style": "soft",
    "instrument_hint": "guitar+piano",
    "is_fill": false,
    "emotional_description": "前向きな決意",
    "suggested_tension": "add9,M7,13th",
    "progression_match": null,
    "matched_chords": [],
    "genre": "EDM",
    "emotional_comment": "",
    "mode": "ionian"
  },
  {
    "offset": 404.0,
    "pitches": [
      "G3",
      "B3",
      "D4"
    ],
    "q_length": 4.0,
    "style": "コードストローク",
    "section": "Chorus 3",
    "chord_label": "",
    "velocity_base": 65,
    "humanize_style": "soft",
    "instrument_hint": "guitar+piano",
    "is_fill": false,
    "emotional_description": "前向きな決意",
    "suggested_tension": "add9,M7,13th",
    "progression_match": null,
    "matched_chords": [],
    "genre": "EDM",
    "emotional_comment": "",
    "mode": "ionian"
  },
  {
    "offset": 408.0,
    "pitches": [
      "Am3",
      "C4",
      "E4"
    ],
    "q_length": 4.0,
    "style": "コードストローク",
    "section": "Chorus 3",
    "chord_label": "",
    "velocity_base": 65,
    "humanize_style": "soft",
    "instrument_hint": "guitar+piano",
    "is_fill": false,
    "emotional_description": "前向きな決意",
    "suggested_tension": "add9,M7,13th",
    "progression_match": null,
    "matched_chords": [],
    "genre": "EDM",
    "emotional_comment": "",
    "mode": "ionian"
  },
  {
    "offset": 412.0,
    "pitches": [
      "C3",
      "E3",
      "G3"
    ],
    "q_length": 4.0,
    "style": "コードストローク",
    "section": "Chorus 3",
    "chord_label": "",
    "velocity_base": 65,
    "humanize_style": "soft",
    "instrument_hint": "guitar+piano",
    "is_fill": false,
    "emotional_description": "前向きな決意",
    "suggested_tension": "add9,M7,13th",
    "progression_match": null,
    "matched_chords": [],
    "genre": "EDM",
    "emotional_comment": "",
    "mode": "ionian"
  },
  {
    "offset": 416.0,
    "pitches": [
      "F3",
      "A3",
      "C4"
    ],
    "q_length": 1.0,
    "style": "コードストローク",
    "section": "Chorus 3",
    "chord_label": "",
    "velocity_base": 65,
    "humanize_style": "soft",
    "instrument_hint": "guitar+piano",
    "is_fill": false,
    "emotional_description": "前向きな決意",
    "suggested_tension": "add9,M7,13th",
    "progression_match": null,
    "matched_chords": [],
    "genre": "EDM",
    "emotional_comment": "",
    "mode": "ionian"
  },
  {
    "offset": 417.0,
    "pitches": [
      "C3",
      "E3",
      "G3"
    ],
    "q_length": 4.0,
    "style": "コードストローク",
    "section": "Bridge 2",
    "chord_label": "",
    "velocity_base": 65,
    "humanize_style": "soft",
    "instrument_hint": "harp+piano",
    "is_fill": false,
    "emotional_description": "静かな望みの輝き",
    "suggested_tension": "add9,sus2",
    "progression_match": null,
    "matched_chords": [],
    "genre": "EDM",
    "emotional_comment": "",
    "mode": "lydian"
  },
  {
    "offset": 421.0,
    "pitches": [
      "F3",
      "A3",
      "C4"
    ],
    "q_length": 4.0,
    "style": "コードストローク",
    "section": "Bridge 2",
    "chord_label": "",
    "velocity_base": 65,
    "humanize_style": "soft",
    "instrument_hint": "harp+piano",
    "is_fill": false,
    "emotional_description": "静かな望みの輝き",
    "suggested_tension": "add9,sus2",
    "progression_match": null,
    "matched_chords": [],
    "genre": "EDM",
    "emotional_comment": "",
    "mode": "lydian"
  },
  {
    "offset": 425.0,
    "pitches": [
      "G3",
      "B3",
      "D4"
    ],
    "q_length": 4.0,
    "style": "コードストローク",
    "section": "Bridge 2",
    "chord_label": "",
    "velocity_base": 65,
    "humanize_style": "soft",
    "instrument_hint": "harp+piano",
    "is_fill": false,
    "emotional_description": "静かな望みの輝き",
    "suggested_tension": "add9,sus2",
    "progression_match": null,
    "matched_chords": [],
    "genre": "EDM",
    "emotional_comment": "",
    "mode": "lydian"
  },
  {
    "offset": 429.0,
    "pitches": [
      "Am3",
      "C4",
      "E4"
    ],
    "q_length": 4.0,
    "style": "コードストローク",
    "section": "Bridge 2",
    "chord_label": "",
    "velocity_base": 65,
    "humanize_style": "soft",
    "instrument_hint": "harp+piano",
    "is_fill": false,
    "emotional_description": "静かな望みの輝き",
    "suggested_tension": "add9,sus2",
    "progression_match": null,
    "matched_chords": [],
    "genre": "EDM",
    "emotional_comment": "",
    "mode": "lydian"
  },
  {
    "offset": 433.0,
    "pitches": [
      "C3",
      "E3",
      "G3"
    ],
    "q_length": 4.0,
    "style": "コードストローク",
    "section": "Bridge 2",
    "chord_label": "",
    "velocity_base": 65,
    "humanize_style": "soft",
    "instrument_hint": "harp+piano",
    "is_fill": false,
    "emotional_description": "静かな望みの輝き",
    "suggested_tension": "add9,sus2",
    "progression_match": null,
    "matched_chords": [],
    "genre": "EDM",
    "emotional_comment": "",
    "mode": "lydian"
  },
  {
    "offset": 437.0,
    "pitches": [
      "F3",
      "A3",
      "C4"
    ],
    "q_length": 4.0,
    "style": "コードストローク",
    "section": "Bridge 2",
    "chord_label": "",
    "velocity_base": 65,
    "humanize_style": "soft",
    "instrument_hint": "harp+piano",
    "is_fill": false,
    "emotional_description": "静かな望みの輝き",
    "suggested_tension": "add9,sus2",
    "progression_match": null,
    "matched_chords": [],
    "genre": "EDM",
    "emotional_comment": "",
    "mode": "lydian"
  },
  {
    "offset": 441.0,
    "pitches": [
      "G3",
      "B3",
      "D4"
    ],
    "q_length": 4.0,
    "style": "コードストローク",
    "section": "Bridge 2",
    "chord_label": "",
    "velocity_base": 65,
    "humanize_style": "soft",
    "instrument_hint": "harp+piano",
    "is_fill": false,
    "emotional_description": "静かな望みの輝き",
    "suggested_tension": "add9,sus2",
    "progression_match": null,
    "matched_chords": [],
    "genre": "EDM",
    "emotional_comment": "",
    "mode": "lydian"
  },
  {
    "offset": 445.0,
    "pitches": [
      "Am3",
      "C4",
      "E4"
    ],
    "q_length": 4.0,
    "style": "コードストローク",
    "section": "Bridge 2",
    "chord_label": "",
    "velocity_base": 65,
    "humanize_style": "soft",
    "instrument_hint": "harp+piano",
    "is_fill": false,
    "emotional_description": "静かな望みの輝き",
    "suggested_tension": "add9,sus2",
    "progression_match": null,
    "matched_chords": [],
    "genre": "EDM",
    "emotional_comment": "",
    "mode": "lydian"
  },
  {
    "offset": 449.0,
    "pitches": [
      "C3",
      "E3",
      "G3"
    ],
    "q_length": 4.0,
    "style": "コードストローク",
    "section": "Verse 4",
    "chord_label": "",
    "velocity_base": 65,
    "humanize_style": "soft",
    "instrument_hint": "harp",
    "is_fill": false,
    "emotional_description": "自然と情感が重なる場面",
    "suggested_tension": "sus2,add9",
    "progression_match": null,
    "matched_chords": [],
    "genre": "EDM",
    "emotional_comment": "",
    "mode": "lydian"
  },
  {
    "offset": 453.0,
    "pitches": [
      "F3",
      "A3",
      "C4"
    ],
    "q_length": 4.0,
    "style": "コードストローク",
    "section": "Verse 4",
    "chord_label": "",
    "velocity_base": 65,
    "humanize_style": "soft",
    "instrument_hint": "harp",
    "is_fill": false,
    "emotional_description": "自然と情感が重なる場面",
    "suggested_tension": "sus2,add9",
    "progression_match": null,
    "matched_chords": [],
    "genre": "EDM",
    "emotional_comment": "",
    "mode": "lydian"
  },
  {
    "offset": 457.0,
    "pitches": [
      "G3",
      "B3",
      "D4"
    ],
    "q_length": 4.0,
    "style": "コードストローク",
    "section": "Verse 4",
    "chord_label": "",
    "velocity_base": 65,
    "humanize_style": "soft",
    "instrument_hint": "harp",
    "is_fill": false,
    "emotional_description": "自然と情感が重なる場面",
    "suggested_tension": "sus2,add9",
    "progression_match": null,
    "matched_chords": [],
    "genre": "EDM",
    "emotional_comment": "",
    "mode": "lydian"
  },
  {
    "offset": 461.0,
    "pitches": [
      "Am3",
      "C4",
      "E4"
    ],
    "q_length": 4.0,
    "style": "コードストローク",
    "section": "Verse 4",
    "chord_label": "",
    "velocity_base": 65,
    "humanize_style": "soft",
    "instrument_hint": "harp",
    "is_fill": false,
    "emotional_description": "自然と情感が重なる場面",
    "suggested_tension": "sus2,add9",
    "progression_match": null,
    "matched_chords": [],
    "genre": "EDM",
    "emotional_comment": "",
    "mode": "lydian"
  },
  {
    "offset": 465.0,
    "pitches": [
      "C3",
      "E3",
      "G3"
    ],
    "q_length": 4.0,
    "style": "コードストローク",
    "section": "Verse 4",
    "chord_label": "",
    "velocity_base": 65,
    "humanize_style": "soft",
    "instrument_hint": "harp",
    "is_fill": false,
    "emotional_description": "自然と情感が重なる場面",
    "suggested_tension": "sus2,add9",
    "progression_match": null,
    "matched_chords": [],
    "genre": "EDM",
    "emotional_comment": "",
    "mode": "lydian"
  },
  {
    "offset": 469.0,
    "pitches": [
      "F3",
      "A3",
      "C4"
    ],
    "q_length": 4.0,
    "style": "コードストローク",
    "section": "Verse 4",
    "chord_label": "",
    "velocity_base": 65,
    "humanize_style": "soft",
    "instrument_hint": "harp",
    "is_fill": false,
    "emotional_description": "自然と情感が重なる場面",
    "suggested_tension": "sus2,add9",
    "progression_match": null,
    "matched_chords": [],
    "genre": "EDM",
    "emotional_comment": "",
    "mode": "lydian"
  },
  {
    "offset": 473.0,
    "pitches": [
      "G3",
      "B3",
      "D4"
    ],
    "q_length": 4.0,
    "style": "コードストローク",
    "section": "Verse 4",
    "chord_label": "",
    "velocity_base": 65,
    "humanize_style": "soft",
    "instrument_hint": "harp",
    "is_fill": false,
    "emotional_description": "自然と情感が重なる場面",
    "suggested_tension": "sus2,add9",
    "progression_match": null,
    "matched_chords": [],
    "genre": "EDM",
    "emotional_comment": "",
    "mode": "lydian"
  },
  {
    "offset": 477.0,
    "pitches": [
      "Am3",
      "C4",
      "E4"
    ],
    "q_length": 4.0,
    "style": "コードストローク",
    "section": "Verse 4",
    "chord_label": "",
    "velocity_base": 65,
    "humanize_style": "soft",
    "instrument_hint": "harp",
    "is_fill": false,
    "emotional_description": "自然と情感が重なる場面",
    "suggested_tension": "sus2,add9",
    "progression_match": null,
    "matched_chords": [],
    "genre": "EDM",
    "emotional_comment": "",
    "mode": "lydian"
  },
  {
    "offset": 481.0,
    "pitches": [
      "C3",
      "E3",
      "G3"
    ],
    "q_length": 4.0,
    "style": "コードストローク",
    "section": "Chorus 4",
    "chord_label": "",
    "velocity_base": 65,
    "humanize_style": "soft",
    "instrument_hint": "guitar+piano",
    "is_fill": false,
    "emotional_description": "戦いぬいの末の私の道",
    "suggested_tension": "add9,M7,7th",
    "progression_match": null,
    "matched_chords": [],
    "genre": "EDM",
    "emotional_comment": "",
    "mode": "ionian"
  },
  {
    "offset": 485.0,
    "pitches": [
      "F3",
      "A3",
      "C4"
    ],
    "q_length": 4.0,
    "style": "コードストローク",
    "section": "Chorus 4",
    "chord_label": "",
    "velocity_base": 65,
    "humanize_style": "soft",
    "instrument_hint": "guitar+piano",
    "is_fill": false,
    "emotional_description": "戦いぬいの末の私の道",
    "suggested_tension": "add9,M7,7th",
    "progression_match": null,
    "matched_chords": [],
    "genre": "EDM",
    "emotional_comment": "",
    "mode": "ionian"
  },
  {
    "offset": 489.0,
    "pitches": [
      "G3",
      "B3",
      "D4"
    ],
    "q_length": 4.0,
    "style": "コードストローク",
    "section": "Chorus 4",
    "chord_label": "",
    "velocity_base": 65,
    "humanize_style": "soft",
    "instrument_hint": "guitar+piano",
    "is_fill": false,
    "emotional_description": "戦いぬいの末の私の道",
    "suggested_tension": "add9,M7,7th",
    "progression_match": null,
    "matched_chords": [],
    "genre": "EDM",
    "emotional_comment": "",
    "mode": "ionian"
  },
  {
    "offset": 493.0,
    "pitches": [
      "Am3",
      "C4",
      "E4"
    ],
    "q_length": 4.0,
    "style": "コードストローク",
    "section": "Chorus 4",
    "chord_label": "",
    "velocity_base": 65,
    "humanize_style": "soft",
    "instrument_hint": "guitar+piano",
    "is_fill": false,
    "emotional_description": "戦いぬいの末の私の道",
    "suggested_tension": "add9,M7,7th",
    "progression_match": null,
    "matched_chords": [],
    "genre": "EDM",
    "emotional_comment": "",
    "mode": "ionian"
  },
  {
    "offset": 497.0,
    "pitches": [
      "C3",
      "E3",
      "G3"
    ],
    "q_length": 4.0,
    "style": "コードストローク",
    "section": "Chorus 4",
    "chord_label": "",
    "velocity_base": 65,
    "humanize_style": "soft",
    "instrument_hint": "guitar+piano",
    "is_fill": false,
    "emotional_description": "戦いぬいの末の私の道",
    "suggested_tension": "add9,M7,7th",
    "progression_match": null,
    "matched_chords": [],
    "genre": "EDM",
    "emotional_comment": "",
    "mode": "ionian"
  },
  {
    "offset": 501.0,
    "pitches": [
      "F3",
      "A3",
      "C4"
    ],
    "q_length": 4.0,
    "style": "コードストローク",
    "section": "Chorus 4",
    "chord_label": "",
    "velocity_base": 65,
    "humanize_style": "soft",
    "instrument_hint": "guitar+piano",
    "is_fill": false,
    "emotional_description": "戦いぬいの末の私の道",
    "suggested_tension": "add9,M7,7th",
    "progression_match": null,
    "matched_chords": [],
    "genre": "EDM",
    "emotional_comment": "",
    "mode": "ionian"
  },
  {
    "offset": 505.0,
    "pitches": [
      "G3",
      "B3",
      "D4"
    ],
    "q_length": 4.0,
    "style": "コードストローク",
    "section": "Chorus 4",
    "chord_label": "",
    "velocity_base": 65,
    "humanize_style": "soft",
    "instrument_hint": "guitar+piano",
    "is_fill": false,
    "emotional_description": "戦いぬいの末の私の道",
    "suggested_tension": "add9,M7,7th",
    "progression_match": null,
    "matched_chords": [],
    "genre": "EDM",
    "emotional_comment": "",
    "mode": "ionian"
  },
  {
    "offset": 509.0,
    "pitches": [
      "Am3",
      "C4",
      "E4"
    ],
    "q_length": 4.0,
    "style": "コードストローク",
    "section": "Chorus 4",
    "chord_label": "",
    "velocity_base": 65,
    "humanize_style": "soft",
    "instrument_hint": "guitar+piano",
    "is_fill": false,
    "emotional_description": "戦いぬいの末の私の道",
    "suggested_tension": "add9,M7,7th",
    "progression_match": null,
    "matched_chords": [],
    "genre": "EDM",
    "emotional_comment": "",
    "mode": "ionian"
  }
]
